README.md
setup.py
src/dg_predictor_kps.egg-info/PKG-INFO
src/dg_predictor_kps.egg-info/SOURCES.txt
src/dg_predictor_kps.egg-info/dependency_links.txt
src/dg_predictor_kps.egg-info/not-zip-safe
src/dg_predictor_kps.egg-info/requires.txt
src/dg_predictor_kps.egg-info/top_level.txt
src/dg_predictor_skeleton/__init__.py
src/dg_predictor_skeleton/predictor.py
src/dg_predictor_skeleton/dg_ltpl_skeleton/__init__.py
src/dg_predictor_skeleton/dg_ltpl_skeleton/skeleton.py